supercell/__init__.py
supercell/models.py
supercell/goes/__init__.py
supercell/highways/__init__.py
supercell/highways/cams.py
supercell/highways/conditions.py
supercell/highways/signs.py
supercell/weatherlink/__init__.py
supercell/weatherlink/exceptions.py
supercell/weatherlink/models.py
supercell/weatherlink/utils.py
python_supercell-1.4.2.dist-info/AUTHORS
python_supercell-1.4.2.dist-info/LICENSE.txt
python_supercell-1.4.2.dist-info/METADATA
python_supercell-1.4.2.dist-info/WHEEL
python_supercell-1.4.2.dist-info/top_level.txt
python_supercell-1.4.2.dist-info/RECORD
